{"cameraMode":{"drawMode":0,"name":"Shaded","section":"Shading Mode"},"sceneLighting":false,"audioPlay":false,"sceneViewState":{"m_AlwaysRefresh":false,"showFog":false,"showSkybox":false,"showFlares":false,"showImageEffects":false,"showParticleSystems":false,"showVisualEffectGraphs":true,"m_FxEnabled":true},"in2DMode":false,"pivot":{"x":21.223875045776368,"y":-2.7415261268615724,"z":25.10733413696289},"rotation":{"x":-0.09737329930067063,"y":-0.2991403341293335,"z":0.03083660453557968,"w":-0.9488260746002197},"size":10.920249938964844,"orthographic":false}